odoo/addons/mail_template_multi_company/README.rst
odoo/addons/mail_template_multi_company/__init__.py
odoo/addons/mail_template_multi_company/__manifest__.py
odoo/addons/mail_template_multi_company/i18n/es.po
odoo/addons/mail_template_multi_company/i18n/it.po
odoo/addons/mail_template_multi_company/i18n/mail_template_multi_company.pot
odoo/addons/mail_template_multi_company/i18n/nl.po
odoo/addons/mail_template_multi_company/models/__init__.py
odoo/addons/mail_template_multi_company/models/mail_template.py
odoo/addons/mail_template_multi_company/readme/CONFIGURE.md
odoo/addons/mail_template_multi_company/readme/CONTRIBUTORS.md
odoo/addons/mail_template_multi_company/readme/DESCRIPTION.md
odoo/addons/mail_template_multi_company/readme/USAGE.md
odoo/addons/mail_template_multi_company/security/mail_template.xml
odoo/addons/mail_template_multi_company/static/description/icon.png
odoo/addons/mail_template_multi_company/static/description/index.html
odoo/addons/mail_template_multi_company/tests/__init__.py
odoo/addons/mail_template_multi_company/tests/test_mail_template.py
odoo/addons/mail_template_multi_company/views/mail_template.xml
odoo_addon_mail_template_multi_company-18.0.1.0.0.2.dist-info/METADATA
odoo_addon_mail_template_multi_company-18.0.1.0.0.2.dist-info/WHEEL
odoo_addon_mail_template_multi_company-18.0.1.0.0.2.dist-info/top_level.txt
odoo_addon_mail_template_multi_company-18.0.1.0.0.2.dist-info/RECORD
